Metadata-Version: 2.1
Name: spherical-opt
Version: 0.3.0
Summary: UNKNOWN
Home-page: https://github.com/philippeller/spherical_opt
Author: Philipp Eller
Author-email: peller.phys@gmail.com
License: Apache 2.0
Platform: UNKNOWN
License-File: LICENSE
